ShenduXuexi500WenFix1/README.md
ShenduXuexi500WenFix1/__init__.py
ShenduXuexi500WenFix1/__main__.py
ShenduXuexi500WenFix1/file.epub
ShenduXuexi500WenFix1/index.html
ShenduXuexi500WenFix1/css/__init__.py
ShenduXuexi500WenFix1/css/annotations.css
ShenduXuexi500WenFix1/css/main.css
ShenduXuexi500WenFix1/css/normalize.css
ShenduXuexi500WenFix1/css/popup.css
ShenduXuexi500WenFix1/font/__init__.py
ShenduXuexi500WenFix1/font/fontello.eot
ShenduXuexi500WenFix1/font/fontello.svg
ShenduXuexi500WenFix1/font/fontello.ttf
ShenduXuexi500WenFix1/font/fontello.woff
ShenduXuexi500WenFix1/img/__init__.py
ShenduXuexi500WenFix1/img/annotator-glyph-sprite.png
ShenduXuexi500WenFix1/img/annotator-icon-sprite.png
ShenduXuexi500WenFix1/img/apple-touch-icon.png
ShenduXuexi500WenFix1/img/cancelfullscreen.png
ShenduXuexi500WenFix1/img/close.png
ShenduXuexi500WenFix1/img/fullscreen.png
ShenduXuexi500WenFix1/img/loader.gif
ShenduXuexi500WenFix1/img/menu-icon.png
ShenduXuexi500WenFix1/img/save.png
ShenduXuexi500WenFix1/img/saved.png
ShenduXuexi500WenFix1/img/settings-s.png
ShenduXuexi500WenFix1/img/settings.png
ShenduXuexi500WenFix1/img/star.png
ShenduXuexi500WenFix1/js/__init__.py
ShenduXuexi500WenFix1/js/epub.js
ShenduXuexi500WenFix1/js/epub.min.js
ShenduXuexi500WenFix1/js/epub.min.map
ShenduXuexi500WenFix1/js/hooks.min.js
ShenduXuexi500WenFix1/js/hooks.min.map
ShenduXuexi500WenFix1/js/reader.js
ShenduXuexi500WenFix1/js/reader.js.map
ShenduXuexi500WenFix1/js/reader.min.js
ShenduXuexi500WenFix1/js/reader.min.map
ShenduXuexi500WenFix1/js/hooks/__init__.py
ShenduXuexi500WenFix1/js/hooks/extensions/__init__.py
ShenduXuexi500WenFix1/js/hooks/extensions/highlight.js
ShenduXuexi500WenFix1/js/libs/__init__.py
ShenduXuexi500WenFix1/js/libs/jquery.min.js
ShenduXuexi500WenFix1/js/libs/localforage.min.js
ShenduXuexi500WenFix1/js/libs/screenfull.js
ShenduXuexi500WenFix1/js/libs/screenfull.min.js
ShenduXuexi500WenFix1/js/libs/zip.min.js
ShenduXuexi500WenFix1/js/plugins/__init__.py
shendu_xuexi_500_wen_fix1-2025.3.24.0.dist-info/METADATA
shendu_xuexi_500_wen_fix1-2025.3.24.0.dist-info/WHEEL
shendu_xuexi_500_wen_fix1-2025.3.24.0.dist-info/entry_points.txt
shendu_xuexi_500_wen_fix1-2025.3.24.0.dist-info/top_level.txt
shendu_xuexi_500_wen_fix1-2025.3.24.0.dist-info/RECORD
